LICENSE
MANIFEST.in
README.md
setup.cfg
setup.py
csplitb/__init__.py
csplitb.egg-info/PKG-INFO
csplitb.egg-info/SOURCES.txt
csplitb.egg-info/dependency_links.txt
csplitb.egg-info/top_level.txt
scripts/csplitb