Metadata-Version: 1.1
Name: csplitb
Version: 1.0.2
Summary: Split binary files on content boundaries
Home-page: https://github.com/mypalmike/csplitb
Author: Michael White
Author-email: csplitb@mypalmike.com
License: UNKNOWN
Platform: UNKNOWN
Classifier: Operating System :: POSIX
Classifier: Development Status :: 5 - Production/Stable
Classifier: Environment :: Console
Classifier: Intended Audience :: System Administrators
Classifier: License :: OSI Approved :: GNU General Public License v2 (GPLv2)
Classifier: Topic :: Utilities
